app/__init__.py
app/core/__init__.py
app/core/base/__init__.py
app/core/base/component.py
app/core/base/observer.py
app/core/base/prompt.py
app/core/base/resource.py
app/core/base/tool.py
app/core/base_mcp.py
app/core/base_prompts.py
app/core/base_resources.py
app/core/base_sampling.py
app/core/config.py
app/core/errors.py
app/core/exceptions.py
app/core/factories/__init__.py
app/core/factories/tool_factory.py
app/core/security.py
app/database.py
app/db/__init__.py
app/db/base.py
app/db/base_class.py
app/db/session.py
app/main.py
app/models/__init__.py
app/models/account.py
app/models/base.py
app/models/graphql.py
app/models/mcp/__init__.py
app/models/mcp/enums.py
app/models/mcp/message.py
app/models/mcp/prompt.py
app/models/mcp/resource.py
app/models/mcp/sampling.py
app/models/mcp/tool.py
app/models/mcp.py
app/models/user.py
app/prompts/__init__.py
app/prompts/prompts.py
app/prompts/registry.py
app/prompts/system_prompts.json
app/prompts/system_prompts.py
app/prompts/user_prompts.json
app/resources/__init__.py
app/resources/registry.py
app/resources/resources.py
app/schemas/__init__.py
app/schemas/token.py
app/services/__init__.py
app/services/mcp_service.py
app/storage/base.py
app/storage/elasticsearch.py
app/storage/redis.py
app/tests/__init__.py
app/tests/conftest/__init__.py
app/tests/conftest.py
app/tests/integration/__init__.py
app/tests/test_endpoints.py
app/tests/unit/__init__.py
app/tools/__init__.py
app/tools/example_tool.py
app/tools/file/__init__.py
app/tools/file/file_system_tool.py
app/tools/file_operations.py
app/tools/registry.py
app/tools/search/__init__.py
app/tools/search/search_tool.py
app/tools/search/strategies/__init__.py
app/tools/search/strategies/faceted_search.py
app/tools/search/strategies/semantic_search.py
app/tools/search/strategies/text_search.py
app/tools/text/__init__.py
app/tools/text/operations/__init__.py
app/tools/text/text_processor_tool.py
app/tools/weather/__init__.py
app/tools/weather/weather_tool.py
app/utils/__init__.py
mseep_myaiserv-0.1.2.dist-info/LICENSE
mseep_myaiserv-0.1.2.dist-info/METADATA
mseep_myaiserv-0.1.2.dist-info/WHEEL
mseep_myaiserv-0.1.2.dist-info/RECORD
