Metadata-Version: 2.3
Name: mseep-myaiserv
Version: 0.1.2
Summary: AI Service with FastAPI
Author: mseep
Author-email: support@skydeck.ai
Maintainer: mseep
Maintainer-email: support@skydeck.ai
Requires-Python: >=3.9,<4.0
Classifier: Programming Language :: Python :: 3
Classifier: Programming Language :: Python :: 3.9
Classifier: Programming Language :: Python :: 3.10
Classifier: Programming Language :: Python :: 3.11
Classifier: Programming Language :: Python :: 3.12
Classifier: Programming Language :: Python :: 3.13
Requires-Dist: aiohttp (>=3.9.3,<4.0.0)
Requires-Dist: elasticsearch (>=8.12.0,<9.0.0)
Requires-Dist: fastapi (>=0.110.0,<0.111.0)
Requires-Dist: httpx (>=0.27.0,<0.28.0)
Requires-Dist: prometheus-fastapi-instrumentator (>=6.1.0,<7.0.0)
Requires-Dist: pytest (>=8.0.0,<9.0.0)
Requires-Dist: pytest-asyncio (>=0.23.5,<0.24.0)
Requires-Dist: pytest-cov (>=4.1.0,<5.0.0)
Requires-Dist: python-magic (>=0.4.27,<0.5.0)
Requires-Dist: redis (>=5.0.3,<6.0.0)
Requires-Dist: strawberry-graphql (>=0.219.1,<0.220.0)
Requires-Dist: uvicorn (>=0.27.1,<0.28.0)
Requires-Dist: websockets (>=12.0,<13.0)
